mcp_community/__init__.py
mcp_community/run.py
mcp_community/cli/__init__.py
mcp_community/cli/main.py
mcp_community/cli/commands/__init__.py
mcp_community/cli/commands/bot.py
mcp_community/servers/README.md
mcp_community/servers/__init__.py
mcp_community/servers/calculator.py
mcp_community/servers/duckduckgo.py
mcp_community-0.0.4.dist-info/METADATA
mcp_community-0.0.4.dist-info/WHEEL
mcp_community-0.0.4.dist-info/entry_points.txt
mcp_community-0.0.4.dist-info/licenses/LICENSE
mcp_community-0.0.4.dist-info/RECORD
