Metadata-Version: 2.4
Name: mcp-community
Version: 0.0.4
Summary: Easily run, deploy, and connect to MCP servers
Project-URL: Homepage, https://mcp.mirascope.com
Project-URL: Documentation, https://mcp.mirascope.com/docs
Project-URL: Repository, https://github.com/Mirascope/mcp-community
Project-URL: Issues, https://github.com/Mirascope/mcp-community/issues
Project-URL: Changelog, https://github.com/Mirascope/mcp-community/releases
Author-email: William Bakst <william@mirascope.com>
Maintainer-email: William Bakst <william@mirascope.com>
License:                                  Apache License
License-File: LICENSE
Keywords: mcp,mcp-server,mirascope,model-context-protocol,model-context-protocol-server
Classifier: Development Status :: 3 - Alpha
Classifier: Intended Audience :: Developers
Classifier: License :: OSI Approved :: Apache Software License
Classifier: Programming Language :: Python :: 3
Classifier: Programming Language :: Python :: 3.10
Classifier: Programming Language :: Python :: 3.11
Classifier: Programming Language :: Python :: 3.12
Classifier: Programming Language :: Python :: 3.13
Classifier: Topic :: Scientific/Engineering :: Artificial Intelligence
Classifier: Topic :: Software Development :: Libraries
Requires-Python: >=3.10
Requires-Dist: mcp>=1.3.0
Requires-Dist: mirascope>=1.21.0
Requires-Dist: rich>=13.9.4
Requires-Dist: typer>=0.9.0
Requires-Dist: uvicorn>=0.29.0
Provides-Extra: bot
Requires-Dist: anthropic>=0.49.0; extra == 'bot'
Provides-Extra: duckduckgo
Requires-Dist: beautifulsoup4>=4.13.3; extra == 'duckduckgo'
Requires-Dist: duckduckgo-search>=7.5.1; extra == 'duckduckgo'
Requires-Dist: pillow>=11.1.0; extra == 'duckduckgo'
Requires-Dist: requests>=2.32.3; extra == 'duckduckgo'
